{
  "project_info": {
    "project_number": "919318565310",
    "project_id": "hopeir-38770",
    "storage_bucket": "hopeir-38770.firebasestorage.app"
  },
  "client": [
    {
      "client_info": {
        "mobilesdk_app_id": "1:919318565310:android:0b022c7158ab7724b829ef",
        "android_client_info": {
          "package_name": "com.hopeir.app"
        }
      },
      "oauth_client": [],
      "api_key": [
        {
          "current_key": "AIzaSyD_MmHNbotnsgrK7BrxuG7FeaTZih3zjfg"
        }
      ],
      "services": {
        "appinvite_service": {
          "other_platform_oauth_client": []
        }
      }
    }
  ],
  "configuration_version": "1"
}